levelling/__init__.py
levelling/abc.py
levelling/dataclass.py
levelling/exceptions.py
levelling/level.py
levelling/options.py
levelling/payloads.py
levelling/store.py
levelling/caches/__init__.py
levelling/caches/memory.py
levelling/datastores/__init__.py
levelling/datastores/json/__init__.py
levelling/datastores/json/json.py
levelling/datastores/sqlite/__init__.py
levelling/datastores/sqlite/sqlite.py
levelling-0.1.4.dist-info/LICENSE
levelling-0.1.4.dist-info/METADATA
levelling-0.1.4.dist-info/WHEEL
levelling-0.1.4.dist-info/top_level.txt
levelling-0.1.4.dist-info/RECORD
