Metadata-Version: 2.1
Name: levelling
Version: 0.1.4
Summary: An easy to use package for levelling features in discord.py.
Home-page: https://github.com/MenuDocs/discord.ext.levelling
Author: Menudocs
Author-email: contact@menudocs.org
License: UNKNOWN
Platform: UNKNOWN
Classifier: Programming Language :: Python :: 3
Classifier: License :: OSI Approved :: MIT License
Classifier: Operating System :: OS Independent
Classifier: Development Status :: 3 - Alpha
Requires-Python: >=3.8
Requires-Dist: aiosqlite
